pandas_zmq
