Metadata-Version: 2.1
Name: pandas-zmq
Version: 0.0.3
Summary: Communicate Pandas DataFrame over ZeroMQ connection
Home-page: https://github.com/rritoch/pandas_zmq
Author: Ralph Ritoch
Author-email: rritoch@gmail.com
License: UNKNOWN
Platform: UNKNOWN
Classifier: Programming Language :: Python :: 3
Classifier: License :: OSI Approved :: MIT License
Classifier: Operating System :: OS Independent
Requires-Python: >=3.3
